dumbemu/__init__.py
dumbemu/context.py
dumbemu/emulator.py
dumbemu/cpu/args.py
dumbemu/cpu/base.py
dumbemu/cpu/regs.py
dumbemu/cpu/x64.py
dumbemu/cpu/x86.py
dumbemu/data/strings.py
dumbemu/data/structs.py
dumbemu/debug/tracer.py
dumbemu/mem/alloc.py
dumbemu/mem/hooks.py
dumbemu/mem/memory.py
dumbemu/mem/stack.py
dumbemu/pe/loader.py
dumbemu/utils/constants.py
dumbemu/utils/logger.py
dumbemu/win/iat.py
dumbemu/win/tebpeb.py
dumbemu-1.0.0.dist-info/METADATA
dumbemu-1.0.0.dist-info/WHEEL
dumbemu-1.0.0.dist-info/top_level.txt
dumbemu-1.0.0.dist-info/RECORD
