Metadata-Version: 2.1
Name: dumbemu
Version: 1.0.0
Summary: A lightweight, performant PE emulator built on Unicorn Engine for Windows executable analysis
Author: Diefunction
License: MIT
Project-URL: Homepage, https://github.com/Diefunction/dumbemu
Project-URL: Bug Tracker, https://github.com/Diefunction/dumbemu/issues
Project-URL: Documentation, https://github.com/Diefunction/dumbemu#readme
Keywords: emulator,pe,windows,unicorn,reverse-engineering,ctf
Classifier: Development Status :: 4 - Beta
Classifier: Intended Audience :: Developers
Classifier: Intended Audience :: Science/Research
Classifier: License :: OSI Approved :: MIT License
Classifier: Programming Language :: Python :: 3
Classifier: Programming Language :: Python :: 3.8
Classifier: Programming Language :: Python :: 3.9
Classifier: Programming Language :: Python :: 3.10
Classifier: Programming Language :: Python :: 3.11
Classifier: Programming Language :: Python :: 3.12
Classifier: Topic :: Security
Classifier: Topic :: Software Development :: Debuggers
Classifier: Topic :: Software Development :: Disassemblers
Requires-Python: >=3.8
Requires-Dist: unicorn >=2.0.0
Requires-Dist: lief >=0.13.0
